django_auto_logout/__init__.py
django_auto_logout/context_processors.py
django_auto_logout/middleware.py
django_auto_logout/utils.py
django_auto_logout-0.5.1.dist-info/LICENSE
django_auto_logout-0.5.1.dist-info/METADATA
django_auto_logout-0.5.1.dist-info/WHEEL
django_auto_logout-0.5.1.dist-info/top_level.txt
django_auto_logout-0.5.1.dist-info/RECORD
