Metadata-Version: 2.1
Name: django-auto-logout
Version: 0.5.1
Summary: Auto logout a user after specific time in Django
Home-page: https://github.com/bugov/django-auto-logout
Author: Georgy Bazhukov
Author-email: georgy.bazhukov@gmail.com
License: BSD
Classifier: Development Status :: 5 - Production/Stable
Classifier: Framework :: Django
Classifier: Framework :: Django :: 3.0
Classifier: Framework :: Django :: 3.1
Classifier: Framework :: Django :: 3.2
Classifier: Intended Audience :: Developers
Classifier: License :: OSI Approved :: BSD License
Classifier: Programming Language :: Python :: 3.7
Classifier: Programming Language :: Python :: 3.8
Classifier: Programming Language :: Python :: 3.9
Classifier: Programming Language :: Python :: 3.10
Requires: django
Requires: setuptools
Requires: wheel
License-File: LICENSE
